[
    {
        "item": "Individual Report",
        "description": "Exploratory data analysis and presentation of insights with visualizations as a junior consultant",
        "weight": "20%"
    },
    {
        "item": "Team Assessment",
        "description": "Team project applying data visualization and predictive analytics to real-world business scenarios for decision-making",
        "weight": "30%"
    },
    {
        "item": "Final Exam",
        "description": "3-hour online exam testing technical competence, problem-solving, and understanding of course concepts across all topics",
        "weight": "50%"
    }
]